Products/validation/ZService.py
Products/validation/__init__.py
Products/validation/chain.py
Products/validation/config.py
Products/validation/configure.zcml
Products/validation/exceptions.py
Products/validation/i18n.py
Products/validation/service.py
Products/validation/interfaces/IValidationService.py
Products/validation/interfaces/IValidator.py
Products/validation/interfaces/__init__.py
Products/validation/locales/README.rst
Products/validation/locales/plone.pot
Products/validation/locales/update.sh
Products/validation/locales/bg/LC_MESSAGES/plone.mo
Products/validation/locales/bg/LC_MESSAGES/plone.po
Products/validation/locales/ca/LC_MESSAGES/plone.mo
Products/validation/locales/ca/LC_MESSAGES/plone.po
Products/validation/locales/cs/LC_MESSAGES/plone.mo
Products/validation/locales/cs/LC_MESSAGES/plone.po
Products/validation/locales/da/LC_MESSAGES/plone.mo
Products/validation/locales/da/LC_MESSAGES/plone.po
Products/validation/locales/de/LC_MESSAGES/plone.mo
Products/validation/locales/de/LC_MESSAGES/plone.po
Products/validation/locales/eo/LC_MESSAGES/plone.mo
Products/validation/locales/eo/LC_MESSAGES/plone.po
Products/validation/locales/es/LC_MESSAGES/plone.mo
Products/validation/locales/es/LC_MESSAGES/plone.po
Products/validation/locales/eu/LC_MESSAGES/plone.mo
Products/validation/locales/eu/LC_MESSAGES/plone.po
Products/validation/locales/fi/LC_MESSAGES/plone.mo
Products/validation/locales/fi/LC_MESSAGES/plone.po
Products/validation/locales/fr/LC_MESSAGES/plone.mo
Products/validation/locales/fr/LC_MESSAGES/plone.po
Products/validation/locales/hi/LC_MESSAGES/plone.mo
Products/validation/locales/hi/LC_MESSAGES/plone.po
Products/validation/locales/id/LC_MESSAGES/plone.mo
Products/validation/locales/id/LC_MESSAGES/plone.po
Products/validation/locales/it/LC_MESSAGES/plone.mo
Products/validation/locales/it/LC_MESSAGES/plone.po
Products/validation/locales/ja/LC_MESSAGES/plone.mo
Products/validation/locales/ja/LC_MESSAGES/plone.po
products_validation-4.0.0.dist-info/METADATA
products_validation-4.0.0.dist-info/WHEEL
products_validation-4.0.0.dist-info/top_level.txt
products_validation-4.0.0.dist-info/RECORD
