Metadata-Version: 2.4
Name: Products.validation
Version: 4.0.0
Summary: Data validation package for Zope
Home-page: https://github.com/plone/Products.validation
Author: Benjamin Saller
Author-email: plone-developers@lists.sourceforge.net
License: GPL
Keywords: Zope validation regex email
Classifier: Development Status :: 6 - Mature
Classifier: Framework :: Zope
Classifier: Framework :: Zope :: 5
Classifier: Operating System :: OS Independent
Classifier: Framework :: Plone
Classifier: Framework :: Plone :: 6.2
Classifier: License :: OSI Approved :: GNU General Public License (GPL)
Classifier: Programming Language :: Python
Classifier: Programming Language :: Python :: 3.10
Classifier: Programming Language :: Python :: 3.11
Classifier: Programming Language :: Python :: 3.12
Classifier: Programming Language :: Python :: 3.13
Requires-Python: >=3.10
Requires-Dist: setuptools
Requires-Dist: Zope
Dynamic: author
Dynamic: author-email
Dynamic: classifier
Dynamic: description
Dynamic: description-content-type
Dynamic: home-page
Dynamic: keywords
Dynamic: license
Dynamic: requires-dist
Dynamic: requires-python
Dynamic: summary
